{"different participants can't be distinguished\n":{"data":{"translations":[{"translatedText":"different participants can not Be Distinguished"}]}},"Other participants ideas are anonymous\n":{"data":{"translations":[{"translatedText":"Other ideas are anonymous participants"}]}},"des supports qui veulent entrer s&#39;il vous plaît":{"data":{"translations":[{"translatedText":"media who want to get s"}]}},"My ideas are highlighted in green\n":{"data":{"translations":[{"translatedText":"My ideas are highlight highlighted in green"}]}},"not":{"data":{"translations":[{"translatedText":"pas"}]}},"be":{"data":{"translations":[{"translatedText":"être"}]}},"supplement":{"data":{"translations":[{"translatedText":"supplément"}]}},"belong":{"data":{"translations":[{"translatedText":"appartenir"}]}},"dwell":{"data":{"translations":[{"translatedText":"séjour"}]}},"translate":{"data":{"translations":[{"translatedText":"traduire"}]}},"exemplify":{"data":{"translations":[{"translatedText":"exemplifier"}]}},"survive":{"data":{"translations":[{"translatedText":"survivre"}]}},"set back":{"data":{"translations":[{"translatedText":"remettre"}]}},"stay":{"data":{"translations":[{"translatedText":"rester"}]}},"highlighter":{"data":{"translations":[{"translatedText":"surligneur"}]}},"take":{"data":{"translations":[{"translatedText":"prendre"}]}},"otherwise":{"data":{"translations":[{"translatedText":"autrement"}]}},"differ":{"data":{"translations":[{"translatedText":"différer"}]}},"nameless":{"data":{"translations":[{"translatedText":"anonyme"}]}},"past":{"data":{"translations":[{"translatedText":"passé"}]}},"likely":{"data":{"translations":[{"translatedText":"probable"}]}},"foreground":{"data":{"translations":[{"translatedText":"premier plan"}]}},"like":{"data":{"translations":[{"translatedText":"comme"}]}},"ketamine":{"data":{"translations":[{"translatedText":"kétamine"}]}},"magnificence":{"data":{"translations":[{"translatedText":"magnificence"}]}},"jade green":{"data":{"translations":[{"translatedText":"jade vert"}]}},"anonymity":{"data":{"translations":[{"translatedText":"anonymat"}]}},"green":{"data":{"translations":[{"translatedText":"vert"}]}},"spinach":{"data":{"translations":[{"translatedText":"épinards"}]}},"otherness":{"data":{"translations":[{"translatedText":"altérité"}]}},"Utah":{"data":{"translations":[{"translatedText":"Utah"}]}},"Green Party":{"data":{"translations":[{"translatedText":"Parti vert"}]}},"greenery":{"data":{"translations":[{"translatedText":"verdure"}]}},"golf course":{"data":{"translations":[{"translatedText":"terrain de golf"}]}},"ill":{"data":{"translations":[{"translatedText":"malade"}]}},"importantly":{"data":{"translations":[{"translatedText":"important"}]}},"important":{"data":{"translations":[{"translatedText":"important"}]}},"labor leader":{"data":{"translations":[{"translatedText":"dirigeant syndical"}]}}}